{
  "company": {
    "name": "Polycab India",
    "short": "Polycab",
    "bse": "542652",
    "nse": "POLYCAB",
    "bucket": "towers_conductors_cables",
    "secondary": null
  },
  "financials": {
    "quarterly": [
      {
        "period_end": "2023-03-31",
        "consolidated": 1,
        "revenue": 4324.0,
        "ebitda": 603.0,
        "pat": 429.0
      },
      {
        "period_end": "2023-06-30",
        "consolidated": 1,
        "revenue": 3889.0,
        "ebitda": 549.0,
        "pat": 403.0
      },
      {
        "period_end": "2023-09-30",
        "consolidated": 1,
        "revenue": 4218.0,
        "ebitda": 609.0,
        "pat": 430.0
      },
      {
        "period_end": "2023-12-31",
        "consolidated": 1,
        "revenue": 4340.0,
        "ebitda": 570.0,
        "pat": 417.0
      },
      {
        "period_end": "2024-03-31",
        "consolidated": 1,
        "revenue": 5592.0,
        "ebitda": 762.0,
        "pat": 553.0
      },
      {
        "period_end": "2024-06-30",
        "consolidated": 1,
        "revenue": 4698.0,
        "ebitda": 583.0,
        "pat": 402.0
      },
      {
        "period_end": "2024-09-30",
        "consolidated": 1,
        "revenue": 5498.0,
        "ebitda": 632.0,
        "pat": 445.0
      },
      {
        "period_end": "2024-12-31",
        "consolidated": 1,
        "revenue": 5226.0,
        "ebitda": 720.0,
        "pat": 464.0
      },
      {
        "period_end": "2025-03-31",
        "consolidated": 1,
        "revenue": 6986.0,
        "ebitda": 1025.0,
        "pat": 734.0
      },
      {
        "period_end": "2025-06-30",
        "consolidated": 1,
        "revenue": 5906.0,
        "ebitda": 858.0,
        "pat": 600.0
      },
      {
        "period_end": "2025-09-30",
        "consolidated": 1,
        "revenue": 6477.0,
        "ebitda": 1021.0,
        "pat": 693.0
      },
      {
        "period_end": "2025-12-31",
        "consolidated": 1,
        "revenue": 7636.0,
        "ebitda": 966.0,
        "pat": 630.0
      },
      {
        "period_end": "2026-03-31",
        "consolidated": 1,
        "revenue": 8864.0,
        "ebitda": 1161.0,
        "pat": 786.0
      }
    ]
  },
  "balance_sheet": [
    {
      "period_end": "2015-03-31",
      "consolidated": 1,
      "equity_capital": 141.0,
      "reserves": 1489.0,
      "borrowings": 546.0,
      "other_liab": 1138.0,
      "total_liab": 3314.0,
      "fixed_assets": 822.0,
      "cwip": 179.0,
      "investments": 0.0,
      "other_assets": 2312.0,
      "total_assets": 3314.0
    },
    {
      "period_end": "2016-03-31",
      "consolidated": 1,
      "equity_capital": 141.0,
      "reserves": 1642.0,
      "borrowings": 796.0,
      "other_liab": 1296.0,
      "total_liab": 3875.0,
      "fixed_assets": 985.0,
      "cwip": 138.0,
      "investments": 0.0,
      "other_assets": 2752.0,
      "total_assets": 3875.0
    },
    {
      "period_end": "2017-03-31",
      "consolidated": 1,
      "equity_capital": 141.0,
      "reserves": 1853.0,
      "borrowings": 856.0,
      "other_liab": 1729.0,
      "total_liab": 4579.0,
      "fixed_assets": 1128.0,
      "cwip": 165.0,
      "investments": 33.0,
      "other_assets": 3253.0,
      "total_assets": 4579.0
    },
    {
      "period_end": "2018-03-31",
      "consolidated": 1,
      "equity_capital": 141.0,
      "reserves": 2206.0,
      "borrowings": 800.0,
      "other_liab": 1300.0,
      "total_liab": 4448.0,
      "fixed_assets": 1197.0,
      "cwip": 136.0,
      "investments": 32.0,
      "other_assets": 3083.0,
      "total_assets": 4448.0
    },
    {
      "period_end": "2019-03-31",
      "consolidated": 1,
      "equity_capital": 141.0,
      "reserves": 2706.0,
      "borrowings": 272.0,
      "other_liab": 2509.0,
      "total_liab": 5628.0,
      "fixed_assets": 1276.0,
      "cwip": 193.0,
      "investments": 29.0,
      "other_assets": 4130.0,
      "total_assets": 5628.0
    },
    {
      "period_end": "2020-03-31",
      "consolidated": 1,
      "equity_capital": 149.0,
      "reserves": 3688.0,
      "borrowings": 157.0,
      "other_liab": 1967.0,
      "total_liab": 5961.0,
      "fixed_assets": 1422.0,
      "cwip": 241.0,
      "investments": 65.0,
      "other_assets": 4232.0,
      "total_assets": 5961.0
    },
    {
      "period_end": "2021-03-31",
      "consolidated": 1,
      "equity_capital": 149.0,
      "reserves": 4605.0,
      "borrowings": 282.0,
      "other_liab": 1978.0,
      "total_liab": 7015.0,
      "fixed_assets": 1870.0,
      "cwip": 99.0,
      "investments": 635.0,
      "other_assets": 4411.0,
      "total_assets": 7015.0
    },
    {
      "period_end": "2022-03-31",
      "consolidated": 1,
      "equity_capital": 149.0,
      "reserves": 5394.0,
      "borrowings": 118.0,
      "other_liab": 1750.0,
      "total_liab": 7412.0,
      "fixed_assets": 1675.0,
      "cwip": 375.0,
      "investments": 773.0,
      "other_assets": 4588.0,
      "total_assets": 7412.0
    },
    {
      "period_end": "2023-03-31",
      "consolidated": 1,
      "equity_capital": 150.0,
      "reserves": 6487.0,
      "borrowings": 109.0,
      "other_liab": 2678.0,
      "total_liab": 9424.0,
      "fixed_assets": 2067.0,
      "cwip": 251.0,
      "investments": 1350.0,
      "other_assets": 5756.0,
      "total_assets": 9424.0
    },
    {
      "period_end": "2024-03-31",
      "consolidated": 1,
      "equity_capital": 150.0,
      "reserves": 8037.0,
      "borrowings": 161.0,
      "other_liab": 3718.0,
      "total_liab": 12066.0,
      "fixed_assets": 2338.0,
      "cwip": 578.0,
      "investments": 1822.0,
      "other_assets": 7328.0,
      "total_assets": 12066.0
    },
    {
      "period_end": "2025-03-31",
      "consolidated": 1,
      "equity_capital": 150.0,
      "reserves": 9675.0,
      "borrowings": 202.0,
      "other_liab": 3721.0,
      "total_liab": 13749.0,
      "fixed_assets": 3011.0,
      "cwip": 708.0,
      "investments": 1749.0,
      "other_assets": 8280.0,
      "total_assets": 13749.0
    },
    {
      "period_end": "2026-03-31",
      "consolidated": 1,
      "equity_capital": 151.0,
      "reserves": 11858.0,
      "borrowings": 236.0,
      "other_liab": 8232.0,
      "total_liab": 20476.0,
      "fixed_assets": 3740.0,
      "cwip": 1139.0,
      "investments": 3405.0,
      "other_assets": 12192.0,
      "total_assets": 20476.0
    }
  ],
  "cash_flow": [
    {
      "period_end": "2015-03-31",
      "consolidated": 1,
      "cfo": 150.0,
      "cfi": -173.0,
      "cff": 15.0,
      "net_cash_flow": -8.0
    },
    {
      "period_end": "2016-03-31",
      "consolidated": 1,
      "cfo": 221.0,
      "cfi": -247.0,
      "cff": 45.0,
      "net_cash_flow": 20.0
    },
    {
      "period_end": "2017-03-31",
      "consolidated": 1,
      "cfo": 296.0,
      "cfi": -295.0,
      "cff": -10.0,
      "net_cash_flow": -8.0
    },
    {
      "period_end": "2018-03-31",
      "consolidated": 1,
      "cfo": 362.0,
      "cfi": -188.0,
      "cff": -190.0,
      "net_cash_flow": -15.0
    },
    {
      "period_end": "2019-03-31",
      "consolidated": 1,
      "cfo": 1230.0,
      "cfi": -408.0,
      "cff": -651.0,
      "net_cash_flow": 171.0
    },
    {
      "period_end": "2020-03-31",
      "consolidated": 1,
      "cfo": 244.0,
      "cfi": -262.0,
      "cff": 11.0,
      "net_cash_flow": -7.0
    },
    {
      "period_end": "2021-03-31",
      "consolidated": 1,
      "cfo": 1252.0,
      "cfi": -1012.0,
      "cff": -175.0,
      "net_cash_flow": 66.0
    },
    {
      "period_end": "2022-03-31",
      "consolidated": 1,
      "cfo": 512.0,
      "cfi": -427.0,
      "cff": -201.0,
      "net_cash_flow": -116.0
    },
    {
      "period_end": "2023-03-31",
      "consolidated": 1,
      "cfo": 1428.0,
      "cfi": -1203.0,
      "cff": -227.0,
      "net_cash_flow": -2.0
    },
    {
      "period_end": "2024-03-31",
      "consolidated": 1,
      "cfo": 1296.0,
      "cfi": -752.0,
      "cff": -387.0,
      "net_cash_flow": 157.0
    },
    {
      "period_end": "2025-03-31",
      "consolidated": 1,
      "cfo": 1809.0,
      "cfi": -1239.0,
      "cff": -628.0,
      "net_cash_flow": -59.0
    },
    {
      "period_end": "2026-03-31",
      "consolidated": 1,
      "cfo": 3811.0,
      "cfi": -2850.0,
      "cff": -799.0,
      "net_cash_flow": 162.0
    }
  ],
  "ratios": [
    {
      "period_end": "2015-03-31",
      "consolidated": 1,
      "debtor_days": 84.0,
      "inventory_days": 95.0,
      "days_payable": 101.0,
      "cash_conv_cycle": 78.0,
      "working_cap_days": 86.0,
      "roce_pct": 17.0
    },
    {
      "period_end": "2016-03-31",
      "consolidated": 1,
      "debtor_days": 95.0,
      "inventory_days": 94.0,
      "days_payable": 101.0,
      "cash_conv_cycle": 88.0,
      "working_cap_days": 94.0,
      "roce_pct": 17.0
    },
    {
      "period_end": "2017-03-31",
      "consolidated": 1,
      "debtor_days": 80.0,
      "inventory_days": 134.0,
      "days_payable": 120.0,
      "cash_conv_cycle": 94.0,
      "working_cap_days": 96.0,
      "roce_pct": 16.0
    },
    {
      "period_end": "2018-03-31",
      "consolidated": 1,
      "debtor_days": 70.0,
      "cash_conv_cycle": 70.0,
      "working_cap_days": 57.0,
      "roce_pct": 22.0
    },
    {
      "period_end": "2019-03-31",
      "consolidated": 1,
      "debtor_days": 61.0,
      "inventory_days": 128.0,
      "days_payable": 97.0,
      "cash_conv_cycle": 91.0,
      "working_cap_days": 45.0,
      "roce_pct": 28.0
    },
    {
      "period_end": "2020-03-31",
      "consolidated": 1,
      "debtor_days": 59.0,
      "inventory_days": 116.0,
      "days_payable": 82.0,
      "cash_conv_cycle": 94.0,
      "working_cap_days": 71.0,
      "roce_pct": 29.0
    },
    {
      "period_end": "2021-03-31",
      "consolidated": 1,
      "debtor_days": 60.0,
      "inventory_days": 113.0,
      "days_payable": 77.0,
      "cash_conv_cycle": 96.0,
      "working_cap_days": 67.0,
      "roce_pct": 23.0
    },
    {
      "period_end": "2022-03-31",
      "consolidated": 1,
      "debtor_days": 39.0,
      "inventory_days": 86.0,
      "days_payable": 48.0,
      "cash_conv_cycle": 77.0,
      "working_cap_days": 67.0,
      "roce_pct": 21.0
    },
    {
      "period_end": "2023-03-31",
      "consolidated": 1,
      "debtor_days": 32.0,
      "inventory_days": 104.0,
      "days_payable": 72.0,
      "cash_conv_cycle": 65.0,
      "working_cap_days": 58.0,
      "roce_pct": 27.0
    },
    {
      "period_end": "2024-03-31",
      "consolidated": 1,
      "debtor_days": 41.0,
      "inventory_days": 105.0,
      "days_payable": 82.0,
      "cash_conv_cycle": 65.0,
      "working_cap_days": 59.0,
      "roce_pct": 31.0
    },
    {
      "period_end": "2025-03-31",
      "consolidated": 1,
      "debtor_days": 42.0,
      "inventory_days": 86.0,
      "days_payable": 64.0,
      "cash_conv_cycle": 64.0,
      "working_cap_days": 54.0,
      "roce_pct": 30.0
    },
    {
      "period_end": "2026-03-31",
      "consolidated": 1,
      "debtor_days": 48.0,
      "inventory_days": 99.0,
      "days_payable": 32.0,
      "cash_conv_cycle": 114.0,
      "working_cap_days": 73.0,
      "roce_pct": 34.0
    }
  ],
  "derived": [
    {
      "period_end": "2015-03-31",
      "period_type": "annual",
      "consolidated": 1,
      "metric": "debt_to_equity",
      "value": 0.33496932515337424,
      "unit": "ratio",
      "formula": "borrowings / net_worth",
      "bucket_rank": 1,
      "bucket_n": 4
    },
    {
      "period_end": "2015-03-31",
      "period_type": "annual",
      "consolidated": 1,
      "metric": "net_worth_inr_cr",
      "value": 1630.0,
      "unit": "INR crore",
      "formula": "equity_capital + reserves",
      "bucket_rank": 1,
      "bucket_n": 4
    },
    {
      "period_end": "2016-03-31",
      "period_type": "annual",
      "consolidated": 1,
      "metric": "capex_proxy_inr_cr",
      "value": 122.0,
      "unit": "INR crore",
      "formula": "delta(fixed_assets + cwip)"
    },
    {
      "period_end": "2016-03-31",
      "period_type": "annual",
      "consolidated": 1,
      "metric": "debt_to_equity",
      "value": 0.4464385866517106,
      "unit": "ratio",
      "formula": "borrowings / net_worth",
      "bucket_rank": 1,
      "bucket_n": 4
    },
    {
      "period_end": "2016-03-31",
      "period_type": "annual",
      "consolidated": 1,
      "metric": "fcf_proxy_inr_cr",
      "value": 99.0,
      "unit": "INR crore",
      "formula": "cfo - capex_proxy",
      "bucket_rank": 3,
      "bucket_n": 4
    },
    {
      "period_end": "2016-03-31",
      "period_type": "annual",
      "consolidated": 1,
      "metric": "net_worth_inr_cr",
      "value": 1783.0,
      "unit": "INR crore",
      "formula": "equity_capital + reserves",
      "bucket_rank": 1,
      "bucket_n": 4
    },
    {
      "period_end": "2017-03-31",
      "period_type": "annual",
      "consolidated": 1,
      "metric": "capex_proxy_inr_cr",
      "value": 170.0,
      "unit": "INR crore",
      "formula": "delta(fixed_assets + cwip)"
    },
    {
      "period_end": "2017-03-31",
      "period_type": "annual",
      "consolidated": 1,
      "metric": "debt_to_equity",
      "value": 0.4292878635907723,
      "unit": "ratio",
      "formula": "borrowings / net_worth",
      "bucket_rank": 2,
      "bucket_n": 4
    },
    {
      "period_end": "2017-03-31",
      "period_type": "annual",
      "consolidated": 1,
      "metric": "fcf_proxy_inr_cr",
      "value": 126.0,
      "unit": "INR crore",
      "formula": "cfo - capex_proxy",
      "bucket_rank": 2,
      "bucket_n": 4
    },
    {
      "period_end": "2017-03-31",
      "period_type": "annual",
      "consolidated": 1,
      "metric": "net_worth_inr_cr",
      "value": 1994.0,
      "unit": "INR crore",
      "formula": "equity_capital + reserves",
      "bucket_rank": 1,
      "bucket_n": 4
    },
    {
      "period_end": "2018-03-31",
      "period_type": "annual",
      "consolidated": 1,
      "metric": "capex_proxy_inr_cr",
      "value": 40.0,
      "unit": "INR crore",
      "formula": "delta(fixed_assets + cwip)"
    },
    {
      "period_end": "2018-03-31",
      "period_type": "annual",
      "consolidated": 1,
      "metric": "debt_to_equity",
      "value": 0.34086067319982954,
      "unit": "ratio",
      "formula": "borrowings / net_worth",
      "bucket_rank": 2,
      "bucket_n": 3
    },
    {
      "period_end": "2018-03-31",
      "period_type": "annual",
      "consolidated": 1,
      "metric": "fcf_proxy_inr_cr",
      "value": 322.0,
      "unit": "INR crore",
      "formula": "cfo - capex_proxy",
      "bucket_rank": 1,
      "bucket_n": 3
    },
    {
      "period_end": "2018-03-31",
      "period_type": "annual",
      "consolidated": 1,
      "metric": "net_worth_inr_cr",
      "value": 2347.0,
      "unit": "INR crore",
      "formula": "equity_capital + reserves",
      "bucket_rank": 1,
      "bucket_n": 3
    },
    {
      "period_end": "2019-03-31",
      "period_type": "annual",
      "consolidated": 1,
      "metric": "capex_proxy_inr_cr",
      "value": 136.0,
      "unit": "INR crore",
      "formula": "delta(fixed_assets + cwip)"
    },
    {
      "period_end": "2019-03-31",
      "period_type": "annual",
      "consolidated": 1,
      "metric": "debt_to_equity",
      "value": 0.09553916403231472,
      "unit": "ratio",
      "formula": "borrowings / net_worth",
      "bucket_rank": 1,
      "bucket_n": 4
    },
    {
      "period_end": "2019-03-31",
      "period_type": "annual",
      "consolidated": 1,
      "metric": "fcf_proxy_inr_cr",
      "value": 1094.0,
      "unit": "INR crore",
      "formula": "cfo - capex_proxy",
      "bucket_rank": 1,
      "bucket_n": 3
    },
    {
      "period_end": "2019-03-31",
      "period_type": "annual",
      "consolidated": 1,
      "metric": "net_worth_inr_cr",
      "value": 2847.0,
      "unit": "INR crore",
      "formula": "equity_capital + reserves",
      "bucket_rank": 1,
      "bucket_n": 4
    },
    {
      "period_end": "2020-03-31",
      "period_type": "annual",
      "consolidated": 1,
      "metric": "capex_proxy_inr_cr",
      "value": 194.0,
      "unit": "INR crore",
      "formula": "delta(fixed_assets + cwip)"
    },
    {
      "period_end": "2020-03-31",
      "period_type": "annual",
      "consolidated": 1,
      "metric": "debt_to_equity",
      "value": 0.040917383372426376,
      "unit": "ratio",
      "formula": "borrowings / net_worth",
      "bucket_rank": 1,
      "bucket_n": 4
    },
    {
      "period_end": "2020-03-31",
      "period_type": "annual",
      "consolidated": 1,
      "metric": "fcf_proxy_inr_cr",
      "value": 50.0,
      "unit": "INR crore",
      "formula": "cfo - capex_proxy",
      "bucket_rank": 2,
      "bucket_n": 4
    },
    {
      "period_end": "2020-03-31",
      "period_type": "annual",
      "consolidated": 1,
      "metric": "net_worth_inr_cr",
      "value": 3837.0,
      "unit": "INR crore",
      "formula": "equity_capital + reserves",
      "bucket_rank": 1,
      "bucket_n": 4
    },
    {
      "period_end": "2021-03-31",
      "period_type": "annual",
      "consolidated": 1,
      "metric": "capex_proxy_inr_cr",
      "value": 306.0,
      "unit": "INR crore",
      "formula": "delta(fixed_assets + cwip)"
    },
    {
      "period_end": "2021-03-31",
      "period_type": "annual",
      "consolidated": 1,
      "metric": "debt_to_equity",
      "value": 0.05931846865797223,
      "unit": "ratio",
      "formula": "borrowings / net_worth",
      "bucket_rank": 1,
      "bucket_n": 4
    },
    {
      "period_end": "2021-03-31",
      "period_type": "annual",
      "consolidated": 1,
      "metric": "fcf_proxy_inr_cr",
      "value": 946.0,
      "unit": "INR crore",
      "formula": "cfo - capex_proxy",
      "bucket_rank": 1,
      "bucket_n": 4
    },
    {
      "period_end": "2021-03-31",
      "period_type": "annual",
      "consolidated": 1,
      "metric": "net_worth_inr_cr",
      "value": 4754.0,
      "unit": "INR crore",
      "formula": "equity_capital + reserves",
      "bucket_rank": 1,
      "bucket_n": 4
    },
    {
      "period_end": "2022-03-31",
      "period_type": "annual",
      "consolidated": 1,
      "metric": "capex_proxy_inr_cr",
      "value": 81.0,
      "unit": "INR crore",
      "formula": "delta(fixed_assets + cwip)"
    },
    {
      "period_end": "2022-03-31",
      "period_type": "annual",
      "consolidated": 1,
      "metric": "debt_to_equity",
      "value": 0.021288111131156414,
      "unit": "ratio",
      "formula": "borrowings / net_worth",
      "bucket_rank": 1,
      "bucket_n": 4
    },
    {
      "period_end": "2022-03-31",
      "period_type": "annual",
      "consolidated": 1,
      "metric": "fcf_proxy_inr_cr",
      "value": 431.0,
      "unit": "INR crore",
      "formula": "cfo - capex_proxy",
      "bucket_rank": 1,
      "bucket_n": 4
    },
    {
      "period_end": "2022-03-31",
      "period_type": "annual",
      "consolidated": 1,
      "metric": "net_worth_inr_cr",
      "value": 5543.0,
      "unit": "INR crore",
      "formula": "equity_capital + reserves",
      "bucket_rank": 1,
      "bucket_n": 4
    },
    {
      "period_end": "2023-03-31",
      "period_type": "annual",
      "consolidated": 1,
      "metric": "capex_proxy_inr_cr",
      "value": 268.0,
      "unit": "INR crore",
      "formula": "delta(fixed_assets + cwip)"
    },
    {
      "period_end": "2023-03-31",
      "period_type": "annual",
      "consolidated": 1,
      "metric": "debt_to_equity",
      "value": 0.016423082718095526,
      "unit": "ratio",
      "formula": "borrowings / net_worth",
      "bucket_rank": 1,
      "bucket_n": 4
    },
    {
      "period_end": "2023-03-31",
      "period_type": "quarterly",
      "consolidated": 1,
      "metric": "ebitda_margin_pct",
      "value": 13.945420906567993,
      "unit": "%",
      "formula": "ebitda/revenue*100",
      "bucket_rank": 1,
      "bucket_n": 4
    },
    {
      "period_end": "2023-03-31",
      "period_type": "annual",
      "consolidated": 1,
      "metric": "fcf_proxy_inr_cr",
      "value": 1160.0,
      "unit": "INR crore",
      "formula": "cfo - capex_proxy",
      "bucket_rank": 1,
      "bucket_n": 4
    },
    {
      "period_end": "2023-03-31",
      "period_type": "quarterly",
      "consolidated": 1,
      "metric": "net_margin_pct",
      "value": 9.9213691026827,
      "unit": "%",
      "formula": "pat/revenue*100",
      "bucket_rank": 1,
      "bucket_n": 4
    },
    {
      "period_end": "2023-03-31",
      "period_type": "annual",
      "consolidated": 1,
      "metric": "net_worth_inr_cr",
      "value": 6637.0,
      "unit": "INR crore",
      "formula": "equity_capital + reserves",
      "bucket_rank": 1,
      "bucket_n": 4
    },
    {
      "period_end": "2023-06-30",
      "period_type": "quarterly",
      "consolidated": 1,
      "metric": "ebitda_margin_pct",
      "value": 14.11673952172795,
      "unit": "%",
      "formula": "ebitda/revenue*100",
      "bucket_rank": 2,
      "bucket_n": 5
    },
    {
      "period_end": "2023-06-30",
      "period_type": "quarterly",
      "consolidated": 1,
      "metric": "net_margin_pct",
      "value": 10.362561069683723,
      "unit": "%",
      "formula": "pat/revenue*100",
      "bucket_rank": 1,
      "bucket_n": 5
    },
    {
      "period_end": "2023-09-30",
      "period_type": "quarterly",
      "consolidated": 1,
      "metric": "ebitda_margin_pct",
      "value": 14.438122332859175,
      "unit": "%",
      "formula": "ebitda/revenue*100",
      "bucket_rank": 1,
      "bucket_n": 5
    },
    {
      "period_end": "2023-09-30",
      "period_type": "quarterly",
      "consolidated": 1,
      "metric": "net_margin_pct",
      "value": 10.194404931247036,
      "unit": "%",
      "formula": "pat/revenue*100",
      "bucket_rank": 1,
      "bucket_n": 5
    },
    {
      "period_end": "2023-12-31",
      "period_type": "quarterly",
      "consolidated": 1,
      "metric": "ebitda_margin_pct",
      "value": 13.13364055299539,
      "unit": "%",
      "formula": "ebitda/revenue*100",
      "bucket_rank": 1,
      "bucket_n": 5
    },
    {
      "period_end": "2023-12-31",
      "period_type": "quarterly",
      "consolidated": 1,
      "metric": "net_margin_pct",
      "value": 9.608294930875577,
      "unit": "%",
      "formula": "pat/revenue*100",
      "bucket_rank": 1,
      "bucket_n": 5
    },
    {
      "period_end": "2024-03-31",
      "period_type": "annual",
      "consolidated": 1,
      "metric": "asset_turnover",
      "value": 1.4950273495773247,
      "unit": "x",
      "formula": "ttm_revenue / total_assets",
      "bucket_rank": 3,
      "bucket_n": 5
    },
    {
      "period_end": "2024-03-31",
      "period_type": "annual",
      "consolidated": 1,
      "metric": "capex_proxy_inr_cr",
      "value": 598.0,
      "unit": "INR crore",
      "formula": "delta(fixed_assets + cwip)"
    },
    {
      "period_end": "2024-03-31",
      "period_type": "annual",
      "consolidated": 1,
      "metric": "cfo_to_ebitda_pct",
      "value": 52.04819277108433,
      "unit": "%",
      "formula": "cfo / ttm_ebitda * 100",
      "bucket_rank": 3,
      "bucket_n": 5
    },
    {
      "period_end": "2024-03-31",
      "period_type": "annual",
      "consolidated": 1,
      "metric": "debt_to_equity",
      "value": 0.019665323073164775,
      "unit": "ratio",
      "formula": "borrowings / net_worth",
      "bucket_rank": 2,
      "bucket_n": 5
    },
    {
      "period_end": "2024-03-31",
      "period_type": "quarterly",
      "consolidated": 1,
      "metric": "ebitda_growth_yoy_pct",
      "value": 26.368159203980102,
      "unit": "%",
      "formula": "ebitda/ebitda_yr_ago - 1",
      "bucket_rank": 2,
      "bucket_n": 4
    },
    {
      "period_end": "2024-03-31",
      "period_type": "quarterly",
      "consolidated": 1,
      "metric": "ebitda_margin_pct",
      "value": 13.626609442060087,
      "unit": "%",
      "formula": "ebitda/revenue*100",
      "bucket_rank": 1,
      "bucket_n": 5
    },
    {
      "period_end": "2024-03-31",
      "period_type": "annual",
      "consolidated": 1,
      "metric": "fcf_proxy_inr_cr",
      "value": 698.0,
      "unit": "INR crore",
      "formula": "cfo - capex_proxy",
      "bucket_rank": 1,
      "bucket_n": 5
    },
    {
      "period_end": "2024-03-31",
      "period_type": "quarterly",
      "consolidated": 1,
      "metric": "net_margin_pct",
      "value": 9.889127324749643,
      "unit": "%",
      "formula": "pat/revenue*100",
      "bucket_rank": 2,
      "bucket_n": 5
    },
    {
      "period_end": "2024-03-31",
      "period_type": "annual",
      "consolidated": 1,
      "metric": "net_worth_inr_cr",
      "value": 8187.0,
      "unit": "INR crore",
      "formula": "equity_capital + reserves",
      "bucket_rank": 1,
      "bucket_n": 5
    },
    {
      "period_end": "2024-03-31",
      "period_type": "quarterly",
      "consolidated": 1,
      "metric": "pat_growth_yoy_pct",
      "value": 28.904428904428904,
      "unit": "%",
      "formula": "pat/pat_yr_ago - 1",
      "bucket_rank": 1,
      "bucket_n": 4
    },
    {
      "period_end": "2024-03-31",
      "period_type": "quarterly",
      "consolidated": 1,
      "metric": "revenue_growth_yoy_pct",
      "value": 29.324699352451432,
      "unit": "%",
      "formula": "rev/rev_yr_ago - 1",
      "bucket_rank": 2,
      "bucket_n": 4
    },
    {
      "period_end": "2024-03-31",
      "period_type": "annual",
      "consolidated": 1,
      "metric": "ttm_ebitda_inr_cr",
      "value": 2490.0,
      "unit": "INR crore",
      "formula": "sum(quarter.ebitda, 4q)",
      "bucket_rank": 1,
      "bucket_n": 5
    },
    {
      "period_end": "2024-03-31",
      "period_type": "annual",
      "consolidated": 1,
      "metric": "ttm_revenue_inr_cr",
      "value": 18039.0,
      "unit": "INR crore",
      "formula": "sum(quarter.revenue, 4q)",
      "bucket_rank": 1,
      "bucket_n": 5
    },
    {
      "period_end": "2024-06-30",
      "period_type": "quarterly",
      "consolidated": 1,
      "metric": "ebitda_growth_yoy_pct",
      "value": 6.193078324225865,
      "unit": "%",
      "formula": "ebitda/ebitda_yr_ago - 1",
      "bucket_rank": 5,
      "bucket_n": 5
    },
    {
      "period_end": "2024-06-30",
      "period_type": "quarterly",
      "consolidated": 1,
      "metric": "ebitda_margin_pct",
      "value": 12.409535972754364,
      "unit": "%",
      "formula": "ebitda/revenue*100",
      "bucket_rank": 1,
      "bucket_n": 5
    },
    {
      "period_end": "2024-06-30",
      "period_type": "quarterly",
      "consolidated": 1,
      "metric": "net_margin_pct",
      "value": 8.55683269476373,
      "unit": "%",
      "formula": "pat/revenue*100",
      "bucket_rank": 1,
      "bucket_n": 5
    },
    {
      "period_end": "2024-06-30",
      "period_type": "quarterly",
      "consolidated": 1,
      "metric": "pat_growth_yoy_pct",
      "value": -0.2481389578163795,
      "unit": "%",
      "formula": "pat/pat_yr_ago - 1",
      "bucket_rank": 5,
      "bucket_n": 5
    },
    {
      "period_end": "2024-06-30",
      "period_type": "quarterly",
      "consolidated": 1,
      "metric": "revenue_growth_yoy_pct",
      "value": 20.802262792491643,
      "unit": "%",
      "formula": "rev/rev_yr_ago - 1",
      "bucket_rank": 3,
      "bucket_n": 5
    },
    {
      "period_end": "2024-09-30",
      "period_type": "quarterly",
      "consolidated": 1,
      "metric": "ebitda_growth_yoy_pct",
      "value": 3.776683087027921,
      "unit": "%",
      "formula": "ebitda/ebitda_yr_ago - 1",
      "bucket_rank": 4,
      "bucket_n": 5
    },
    {
      "period_end": "2024-09-30",
      "period_type": "quarterly",
      "consolidated": 1,
      "metric": "ebitda_margin_pct",
      "value": 11.49508912331757,
      "unit": "%",
      "formula": "ebitda/revenue*100",
      "bucket_rank": 1,
      "bucket_n": 5
    },
    {
      "period_end": "2024-09-30",
      "period_type": "quarterly",
      "consolidated": 1,
      "metric": "net_margin_pct",
      "value": 8.093852309930885,
      "unit": "%",
      "formula": "pat/revenue*100",
      "bucket_rank": 1,
      "bucket_n": 5
    },
    {
      "period_end": "2024-09-30",
      "period_type": "quarterly",
      "consolidated": 1,
      "metric": "pat_growth_yoy_pct",
      "value": 3.488372093023262,
      "unit": "%",
      "formula": "pat/pat_yr_ago - 1",
      "bucket_rank": 5,
      "bucket_n": 5
    },
    {
      "period_end": "2024-09-30",
      "period_type": "quarterly",
      "consolidated": 1,
      "metric": "revenue_growth_yoy_pct",
      "value": 30.346135609293512,
      "unit": "%",
      "formula": "rev/rev_yr_ago - 1",
      "bucket_rank": 3,
      "bucket_n": 5
    },
    {
      "period_end": "2024-12-31",
      "period_type": "quarterly",
      "consolidated": 1,
      "metric": "ebitda_growth_yoy_pct",
      "value": 26.315789473684205,
      "unit": "%",
      "formula": "ebitda/ebitda_yr_ago - 1",
      "bucket_rank": 3,
      "bucket_n": 5
    },
    {
      "period_end": "2024-12-31",
      "period_type": "quarterly",
      "consolidated": 1,
      "metric": "ebitda_margin_pct",
      "value": 13.777267508610791,
      "unit": "%",
      "formula": "ebitda/revenue*100",
      "bucket_rank": 1,
      "bucket_n": 5
    },
    {
      "period_end": "2024-12-31",
      "period_type": "quarterly",
      "consolidated": 1,
      "metric": "net_margin_pct",
      "value": 8.878683505549176,
      "unit": "%",
      "formula": "pat/revenue*100",
      "bucket_rank": 1,
      "bucket_n": 5
    },
    {
      "period_end": "2024-12-31",
      "period_type": "quarterly",
      "consolidated": 1,
      "metric": "pat_growth_yoy_pct",
      "value": 11.270983213429254,
      "unit": "%",
      "formula": "pat/pat_yr_ago - 1",
      "bucket_rank": 2,
      "bucket_n": 5
    },
    {
      "period_end": "2024-12-31",
      "period_type": "quarterly",
      "consolidated": 1,
      "metric": "revenue_growth_yoy_pct",
      "value": 20.414746543778794,
      "unit": "%",
      "formula": "rev/rev_yr_ago - 1",
      "bucket_rank": 3,
      "bucket_n": 5
    },
    {
      "period_end": "2025-03-31",
      "period_type": "annual",
      "consolidated": 1,
      "metric": "asset_turnover",
      "value": 1.6297912575460034,
      "unit": "x",
      "formula": "ttm_revenue / total_assets",
      "bucket_rank": 2,
      "bucket_n": 5
    },
    {
      "period_end": "2025-03-31",
      "period_type": "annual",
      "consolidated": 1,
      "metric": "capex_proxy_inr_cr",
      "value": 803.0,
      "unit": "INR crore",
      "formula": "delta(fixed_assets + cwip)"
    },
    {
      "period_end": "2025-03-31",
      "period_type": "annual",
      "consolidated": 1,
      "metric": "cfo_to_ebitda_pct",
      "value": 61.114864864864856,
      "unit": "%",
      "formula": "cfo / ttm_ebitda * 100",
      "bucket_rank": 3,
      "bucket_n": 5
    },
    {
      "period_end": "2025-03-31",
      "period_type": "annual",
      "consolidated": 1,
      "metric": "debt_to_equity",
      "value": 0.020559796437659032,
      "unit": "ratio",
      "formula": "borrowings / net_worth",
      "bucket_rank": 2,
      "bucket_n": 5
    },
    {
      "period_end": "2025-03-31",
      "period_type": "quarterly",
      "consolidated": 1,
      "metric": "ebitda_growth_yoy_pct",
      "value": 34.51443569553805,
      "unit": "%",
      "formula": "ebitda/ebitda_yr_ago - 1",
      "bucket_rank": 1,
      "bucket_n": 5
    },
    {
      "period_end": "2025-03-31",
      "period_type": "quarterly",
      "consolidated": 1,
      "metric": "ebitda_margin_pct",
      "value": 14.67220154594904,
      "unit": "%",
      "formula": "ebitda/revenue*100",
      "bucket_rank": 1,
      "bucket_n": 5
    },
    {
      "period_end": "2025-03-31",
      "period_type": "annual",
      "consolidated": 1,
      "metric": "fcf_proxy_inr_cr",
      "value": 1006.0,
      "unit": "INR crore",
      "formula": "cfo - capex_proxy",
      "bucket_rank": 1,
      "bucket_n": 5
    },
    {
      "period_end": "2025-03-31",
      "period_type": "quarterly",
      "consolidated": 1,
      "metric": "net_margin_pct",
      "value": 10.506727741196679,
      "unit": "%",
      "formula": "pat/revenue*100",
      "bucket_rank": 1,
      "bucket_n": 5
    },
    {
      "period_end": "2025-03-31",
      "period_type": "annual",
      "consolidated": 1,
      "metric": "net_worth_inr_cr",
      "value": 9825.0,
      "unit": "INR crore",
      "formula": "equity_capital + reserves",
      "bucket_rank": 1,
      "bucket_n": 5
    },
    {
      "period_end": "2025-03-31",
      "period_type": "quarterly",
      "consolidated": 1,
      "metric": "pat_growth_yoy_pct",
      "value": 32.73056057866184,
      "unit": "%",
      "formula": "pat/pat_yr_ago - 1",
      "bucket_rank": 3,
      "bucket_n": 5
    },
    {
      "period_end": "2025-03-31",
      "period_type": "quarterly",
      "consolidated": 1,
      "metric": "revenue_growth_yoy_pct",
      "value": 24.928469241773964,
      "unit": "%",
      "formula": "rev/rev_yr_ago - 1",
      "bucket_rank": 3,
      "bucket_n": 5
    },
    {
      "period_end": "2025-03-31",
      "period_type": "annual",
      "consolidated": 1,
      "metric": "ttm_ebitda_inr_cr",
      "value": 2960.0,
      "unit": "INR crore",
      "formula": "sum(quarter.ebitda, 4q)",
      "bucket_rank": 1,
      "bucket_n": 5
    },
    {
      "period_end": "2025-03-31",
      "period_type": "annual",
      "consolidated": 1,
      "metric": "ttm_revenue_inr_cr",
      "value": 22408.0,
      "unit": "INR crore",
      "formula": "sum(quarter.revenue, 4q)",
      "bucket_rank": 1,
      "bucket_n": 5
    },
    {
      "period_end": "2025-06-30",
      "period_type": "quarterly",
      "consolidated": 1,
      "metric": "ebitda_growth_yoy_pct",
      "value": 47.169811320754704,
      "unit": "%",
      "formula": "ebitda/ebitda_yr_ago - 1",
      "bucket_rank": 1,
      "bucket_n": 5
    },
    {
      "period_end": "2025-06-30",
      "period_type": "quarterly",
      "consolidated": 1,
      "metric": "ebitda_margin_pct",
      "value": 14.527599051811718,
      "unit": "%",
      "formula": "ebitda/revenue*100",
      "bucket_rank": 1,
      "bucket_n": 5
    },
    {
      "period_end": "2025-06-30",
      "period_type": "quarterly",
      "consolidated": 1,
      "metric": "net_margin_pct",
      "value": 10.15916017609211,
      "unit": "%",
      "formula": "pat/revenue*100",
      "bucket_rank": 1,
      "bucket_n": 5
    },
    {
      "period_end": "2025-06-30",
      "period_type": "quarterly",
      "consolidated": 1,
      "metric": "pat_growth_yoy_pct",
      "value": 49.25373134328359,
      "unit": "%",
      "formula": "pat/pat_yr_ago - 1",
      "bucket_rank": 1,
      "bucket_n": 5
    },
    {
      "period_end": "2025-06-30",
      "period_type": "quarterly",
      "consolidated": 1,
      "metric": "revenue_growth_yoy_pct",
      "value": 25.713069391230302,
      "unit": "%",
      "formula": "rev/rev_yr_ago - 1",
      "bucket_rank": 3,
      "bucket_n": 5
    },
    {
      "period_end": "2025-09-30",
      "period_type": "quarterly",
      "consolidated": 1,
      "metric": "ebitda_growth_yoy_pct",
      "value": 61.5506329113924,
      "unit": "%",
      "formula": "ebitda/ebitda_yr_ago - 1",
      "bucket_rank": 2,
      "bucket_n": 5
    },
    {
      "period_end": "2025-09-30",
      "period_type": "quarterly",
      "consolidated": 1,
      "metric": "ebitda_margin_pct",
      "value": 15.76347074262776,
      "unit": "%",
      "formula": "ebitda/revenue*100",
      "bucket_rank": 1,
      "bucket_n": 5
    },
    {
      "period_end": "2025-09-30",
      "period_type": "quarterly",
      "consolidated": 1,
      "metric": "net_margin_pct",
      "value": 10.699397869383974,
      "unit": "%",
      "formula": "pat/revenue*100",
      "bucket_rank": 1,
      "bucket_n": 5
    },
    {
      "period_end": "2025-09-30",
      "period_type": "quarterly",
      "consolidated": 1,
      "metric": "pat_growth_yoy_pct",
      "value": 55.730337078651694,
      "unit": "%",
      "formula": "pat/pat_yr_ago - 1",
      "bucket_rank": 2,
      "bucket_n": 5
    },
    {
      "period_end": "2025-09-30",
      "period_type": "quarterly",
      "consolidated": 1,
      "metric": "revenue_growth_yoy_pct",
      "value": 17.80647508184794,
      "unit": "%",
      "formula": "rev/rev_yr_ago - 1",
      "bucket_rank": 4,
      "bucket_n": 5
    },
    {
      "period_end": "2025-12-31",
      "period_type": "quarterly",
      "consolidated": 1,
      "metric": "ebitda_growth_yoy_pct",
      "value": 34.16666666666666,
      "unit": "%",
      "formula": "ebitda/ebitda_yr_ago - 1",
      "bucket_rank": 2,
      "bucket_n": 5
    },
    {
      "period_end": "2025-12-31",
      "period_type": "quarterly",
      "consolidated": 1,
      "metric": "ebitda_margin_pct",
      "value": 12.650602409638553,
      "unit": "%",
      "formula": "ebitda/revenue*100",
      "bucket_rank": 2,
      "bucket_n": 5
    },
    {
      "period_end": "2025-12-31",
      "period_type": "quarterly",
      "consolidated": 1,
      "metric": "net_margin_pct",
      "value": 8.250392875851231,
      "unit": "%",
      "formula": "pat/revenue*100",
      "bucket_rank": 2,
      "bucket_n": 5
    },
    {
      "period_end": "2025-12-31",
      "period_type": "quarterly",
      "consolidated": 1,
      "metric": "pat_growth_yoy_pct",
      "value": 35.77586206896552,
      "unit": "%",
      "formula": "pat/pat_yr_ago - 1",
      "bucket_rank": 4,
      "bucket_n": 5
    },
    {
      "period_end": "2025-12-31",
      "period_type": "quarterly",
      "consolidated": 1,
      "metric": "revenue_growth_yoy_pct",
      "value": 46.11557596632223,
      "unit": "%",
      "formula": "rev/rev_yr_ago - 1",
      "bucket_rank": 2,
      "bucket_n": 5
    },
    {
      "period_end": "2026-03-31",
      "period_type": "annual",
      "consolidated": 1,
      "metric": "asset_turnover",
      "value": 1.410578237937097,
      "unit": "x",
      "formula": "ttm_revenue / total_assets",
      "bucket_rank": 1,
      "bucket_n": 3
    },
    {
      "period_end": "2026-03-31",
      "period_type": "annual",
      "consolidated": 1,
      "metric": "capex_proxy_inr_cr",
      "value": 1160.0,
      "unit": "INR crore",
      "formula": "delta(fixed_assets + cwip)"
    },
    {
      "period_end": "2026-03-31",
      "period_type": "annual",
      "consolidated": 1,
      "metric": "cfo_to_ebitda_pct",
      "value": 95.13230154767848,
      "unit": "%",
      "formula": "cfo / ttm_ebitda * 100",
      "bucket_rank": 1,
      "bucket_n": 3
    },
    {
      "period_end": "2026-03-31",
      "period_type": "annual",
      "consolidated": 1,
      "metric": "debt_to_equity",
      "value": 0.01965192772087601,
      "unit": "ratio",
      "formula": "borrowings / net_worth",
      "bucket_rank": 1,
      "bucket_n": 3
    },
    {
      "period_end": "2026-03-31",
      "period_type": "quarterly",
      "consolidated": 1,
      "metric": "ebitda_growth_yoy_pct",
      "value": 13.26829268292682,
      "unit": "%",
      "formula": "ebitda/ebitda_yr_ago - 1",
      "bucket_rank": 3,
      "bucket_n": 3
    },
    {
      "period_end": "2026-03-31",
      "period_type": "quarterly",
      "consolidated": 1,
      "metric": "ebitda_margin_pct",
      "value": 13.097924187725631,
      "unit": "%",
      "formula": "ebitda/revenue*100",
      "bucket_rank": 1,
      "bucket_n": 3
    },
    {
      "period_end": "2026-03-31",
      "period_type": "annual",
      "consolidated": 1,
      "metric": "fcf_proxy_inr_cr",
      "value": 2651.0,
      "unit": "INR crore",
      "formula": "cfo - capex_proxy",
      "bucket_rank": 1,
      "bucket_n": 3
    },
    {
      "period_end": "2026-03-31",
      "period_type": "quarterly",
      "consolidated": 1,
      "metric": "net_margin_pct",
      "value": 8.867328519855596,
      "unit": "%",
      "formula": "pat/revenue*100",
      "bucket_rank": 1,
      "bucket_n": 3
    },
    {
      "period_end": "2026-03-31",
      "period_type": "annual",
      "consolidated": 1,
      "metric": "net_worth_inr_cr",
      "value": 12009.0,
      "unit": "INR crore",
      "formula": "equity_capital + reserves",
      "bucket_rank": 1,
      "bucket_n": 3
    },
    {
      "period_end": "2026-03-31",
      "period_type": "quarterly",
      "consolidated": 1,
      "metric": "pat_growth_yoy_pct",
      "value": 7.08446866485013,
      "unit": "%",
      "formula": "pat/pat_yr_ago - 1",
      "bucket_rank": 3,
      "bucket_n": 3
    },
    {
      "period_end": "2026-03-31",
      "period_type": "quarterly",
      "consolidated": 1,
      "metric": "revenue_growth_yoy_pct",
      "value": 26.882336100772974,
      "unit": "%",
      "formula": "rev/rev_yr_ago - 1",
      "bucket_rank": 2,
      "bucket_n": 3
    },
    {
      "period_end": "2026-03-31",
      "period_type": "annual",
      "consolidated": 1,
      "metric": "ttm_ebitda_inr_cr",
      "value": 4006.0,
      "unit": "INR crore",
      "formula": "sum(quarter.ebitda, 4q)",
      "bucket_rank": 1,
      "bucket_n": 3
    },
    {
      "period_end": "2026-03-31",
      "period_type": "annual",
      "consolidated": 1,
      "metric": "ttm_revenue_inr_cr",
      "value": 28883.0,
      "unit": "INR crore",
      "formula": "sum(quarter.revenue, 4q)",
      "bucket_rank": 1,
      "bucket_n": 3
    }
  ],
  "market": {
    "price": null,
    "pct_change": null,
    "market_cap_cr": null,
    "pe_ratio": 52.76,
    "pb_ratio": 16.14,
    "dividend_yield": null,
    "week52_high": null,
    "week52_low": null,
    "book_value": null,
    "eps": 173.43,
    "face_value": null,
    "fetched_at": "2026-05-18T09:50:22+00:00"
  },
  "documents": [
    {
      "doc_kind": "results",
      "page_count": null,
      "pdf_url": "https://www.bseindia.com/xml-data/corpfiling/AttachLive/0a6e3316-d562-4a37-94a4-acc847142461.pdf",
      "extract_status": "failed",
      "extracted_at": "2026-05-18T09:50:39+00:00",
      "has_text": false
    },
    {
      "doc_kind": "press_release",
      "page_count": null,
      "pdf_url": "https://www.bseindia.com/xml-data/corpfiling/AttachLive/157237ff-292b-4fd7-8232-082b9eec2da9.pdf",
      "extract_status": "failed",
      "extracted_at": "2026-05-18T09:50:39+00:00",
      "has_text": false
    },
    {
      "doc_kind": "investor_presentation",
      "page_count": null,
      "pdf_url": "https://www.bseindia.com/xml-data/corpfiling/AttachLive/ab476332-03d9-4198-a861-0c9bfc692894.pdf",
      "extract_status": "failed",
      "extracted_at": "2026-05-18T09:50:39+00:00",
      "has_text": false
    },
    {
      "doc_kind": "transcript",
      "page_count": null,
      "pdf_url": "https://www.bseindia.com/xml-data/corpfiling/AttachLive/c54bf2c3-22fa-45e1-bf1a-2194e7b46183.pdf",
      "extract_status": "failed",
      "extracted_at": "2026-05-18T09:50:39+00:00",
      "has_text": false
    },
    {
      "doc_kind": "transcript",
      "page_count": null,
      "pdf_url": "https://www.bseindia.com/xml-data/corpfiling/AttachLive/2d9d277e-446e-43f7-b7e2-45421ce8d1ce.pdf",
      "extract_status": "failed",
      "extracted_at": "2026-05-18T09:50:39+00:00",
      "has_text": false
    },
    {
      "doc_kind": "investor_presentation",
      "page_count": null,
      "pdf_url": "https://www.bseindia.com/xml-data/corpfiling/AttachLive/9b665a82-e6f7-42aa-8d23-b4cc3572bac1.pdf",
      "extract_status": "failed",
      "extracted_at": "2026-05-18T09:50:39+00:00",
      "has_text": false
    },
    {
      "doc_kind": "investor_presentation",
      "page_count": null,
      "pdf_url": "https://www.bseindia.com/xml-data/corpfiling/AttachLive/8de524ad-06c7-45d8-a078-ac4d0174164e.pdf",
      "extract_status": "failed",
      "extracted_at": "2026-05-18T09:50:39+00:00",
      "has_text": false
    },
    {
      "doc_kind": "results",
      "page_count": null,
      "pdf_url": "https://www.bseindia.com/xml-data/corpfiling/AttachLive/68a7423d-4624-4237-bbdd-9b7b6cd13341.pdf",
      "extract_status": "failed",
      "extracted_at": "2026-05-18T09:50:39+00:00",
      "has_text": false
    },
    {
      "doc_kind": "transcript",
      "page_count": 19,
      "pdf_url": "https://www.bseindia.com/xml-data/corpfiling/AttachLive/f66f17ac-c40f-4309-afca-3e66af0956a0.pdf",
      "extract_status": "ok",
      "extracted_at": "2026-05-18T08:42:58+00:00",
      "has_text": true
    },
    {
      "doc_kind": "transcript",
      "page_count": 1,
      "pdf_url": "https://www.bseindia.com/xml-data/corpfiling/AttachLive/9c9ecf50-f569-41b4-a60c-9d75c87430a3.pdf",
      "extract_status": "ok",
      "extracted_at": "2026-05-18T08:42:58+00:00",
      "has_text": true
    },
    {
      "doc_kind": "results",
      "page_count": 67,
      "pdf_url": "https://www.bseindia.com/xml-data/corpfiling/AttachLive/382214c5-2ac2-492e-9d90-3577e9222e98.pdf",
      "extract_status": "ok",
      "extracted_at": "2026-05-18T08:42:58+00:00",
      "has_text": true
    },
    {
      "doc_kind": "results",
      "page_count": 31,
      "pdf_url": "https://www.bseindia.com/xml-data/corpfiling/AttachLive/0f586954-cf4c-4a5c-b179-8fb4a3cf55a9.pdf",
      "extract_status": "ok",
      "extracted_at": "2026-05-18T08:42:58+00:00",
      "has_text": true
    },
    {
      "doc_kind": "results",
      "page_count": 24,
      "pdf_url": "https://www.bseindia.com/xml-data/corpfiling/AttachLive/1538e3eb-56c6-4ad2-a1ea-a25b2291b09e.pdf",
      "extract_status": "ok",
      "extracted_at": "2026-05-18T08:42:58+00:00",
      "has_text": true
    },
    {
      "doc_kind": "results",
      "page_count": 24,
      "pdf_url": "https://www.bseindia.com/xml-data/corpfiling/AttachLive/c3d48125-e306-4274-bc87-1ba06eb6607f.pdf",
      "extract_status": "ok",
      "extracted_at": "2026-05-18T08:42:58+00:00",
      "has_text": true
    },
    {
      "doc_kind": "transcript",
      "page_count": 3,
      "pdf_url": "https://www.bseindia.com/xml-data/corpfiling/AttachLive/ad900e50-8fcc-4834-80bb-81c1e446a190.pdf",
      "extract_status": "ok",
      "extracted_at": "2026-05-18T08:42:58+00:00",
      "has_text": true
    }
  ],
  "features": {},
  "scorecard": [
    {
      "factor": "approval_technology_depth",
      "score": null,
      "evidence": "insufficient data",
      "inputs": {}
    },
    {
      "factor": "balance_sheet",
      "score": 5,
      "evidence": "debt/equity = 0.02",
      "inputs": {
        "debt_to_equity": 0.01965192772087601
      }
    },
    {
      "factor": "capacity_readiness",
      "score": null,
      "evidence": "insufficient data",
      "inputs": {}
    },
    {
      "factor": "competitive_position",
      "score": 5,
      "evidence": "revenue rank 1/3, ebitda-margin rank 1/3",
      "inputs": {
        "revenue_rank": 1,
        "revenue_n": 3,
        "ebitda_margin_rank": 1,
        "ebitda_margin_n": 3
      }
    },
    {
      "factor": "margin_sustainability",
      "score": 5,
      "evidence": "ebitda_margin=13.1% (peer rank 1/3), yoy_growth=13%",
      "inputs": {
        "ebitda_margin_pct": 13.097924187725631,
        "ebitda_growth_yoy_pct": 13.26829268292682,
        "peer_rank": 1,
        "peer_n": 3
      }
    },
    {
      "factor": "order_book_quality",
      "score": null,
      "evidence": "insufficient data",
      "inputs": {}
    },
    {
      "factor": "tam_relevance",
      "score": 2,
      "evidence": "order_wins=0, capex_mentions=0",
      "inputs": {
        "order_wins": 0,
        "capex_mentions": 0
      }
    },
    {
      "factor": "valuation_comfort",
      "score": 4,
      "evidence": "proxy (no market-cap feed yet): rev_growth=26.882336100772974, ebitda_margin=13.097924187725631, debt/eq=0.01965192772087601",
      "inputs": {
        "rev_growth_yoy_pct": 26.882336100772974,
        "ebitda_margin_pct": 13.097924187725631,
        "debt_to_equity": 0.01965192772087601
      }
    },
    {
      "factor": "value_chain_quality",
      "score": null,
      "evidence": "insufficient data",
      "inputs": {}
    },
    {
      "factor": "working_capital",
      "score": 5,
      "evidence": "wc_days=73.0, debtor_days=48.0, cfo/ebitda=95%",
      "inputs": {
        "working_cap_days": 73.0,
        "debtor_days": 48.0,
        "cfo_to_ebitda_pct": 95.13230154767848
      }
    }
  ],
  "coverage_pct": 62,
  "coverage_checks": {
    "has_quarterly_financials": true,
    "has_balance_sheet": true,
    "has_cash_flow": true,
    "has_ratios": true,
    "has_market_data": true,
    "has_documents_text": true,
    "has_voltage_features": false,
    "has_capacity_features": false,
    "has_order_features": false,
    "has_customer_features": false,
    "has_capex_features": false,
    "has_derived_margins": true,
    "has_derived_growth": true,
    "has_derived_balance_sheet": true,
    "has_peer_ranks": true,
    "has_scorecard_complete": false
  }
}